gensim/__init__.py
gensim/_matutils.c
gensim/_matutils.cp311-win_amd64.pyd
gensim/_matutils.pyx
gensim/downloader.py
gensim/interfaces.py
gensim/matutils.py
gensim/nosy.py
gensim/utils.py
gensim/corpora/__init__.py
gensim/corpora/_mmreader.c
gensim/corpora/_mmreader.cp311-win_amd64.pyd
gensim/corpora/_mmreader.pyx
gensim/corpora/bleicorpus.py
gensim/corpora/csvcorpus.py
gensim/corpora/dictionary.py
gensim/corpora/hashdictionary.py
gensim/corpora/indexedcorpus.py
gensim/corpora/lowcorpus.py
gensim/corpora/malletcorpus.py
gensim/corpora/mmcorpus.py
gensim/corpora/opinosiscorpus.py
gensim/corpora/sharded_corpus.py
gensim/corpora/svmlightcorpus.py
gensim/corpora/textcorpus.py
gensim/corpora/ucicorpus.py
gensim/corpora/wikicorpus.py
gensim/models/__init__.py
gensim/models/_fasttext_bin.py
gensim/models/atmodel.py
gensim/models/basemodel.py
gensim/models/bm25model.py
gensim/models/callbacks.py
gensim/models/coherencemodel.py
gensim/models/doc2vec.py
gensim/models/doc2vec_corpusfile.cp311-win_amd64.pyd
gensim/models/doc2vec_corpusfile.cpp
gensim/models/doc2vec_corpusfile.pyx
gensim/models/doc2vec_inner.cp311-win_amd64.pyd
gensim/models/doc2vec_inner.cpp
gensim/models/doc2vec_inner.pxd
gensim/models/doc2vec_inner.pyx
gensim/models/ensemblelda.py
gensim/models/fast_line_sentence.h
gensim/models/fasttext.py
gensim/models/fasttext_corpusfile.cp311-win_amd64.pyd
gensim/models/fasttext_corpusfile.cpp
gensim/models/fasttext_corpusfile.pyx
gensim/models/fasttext_inner.c
gensim/models/fasttext_inner.cp311-win_amd64.pyd
gensim/models/fasttext_inner.pxd
gensim/models/fasttext_inner.pyx
gensim/models/hdpmodel.py
gensim/models/keyedvectors.py
gensim/models/lda_dispatcher.py
gensim/models/lda_worker.py
gensim/models/ldamodel.py
gensim/models/ldamulticore.py
gensim/models/ldaseqmodel.py
gensim/models/logentropy_model.py
gensim/models/lsi_dispatcher.py
gensim/models/lsi_worker.py
gensim/models/lsimodel.py
gensim/models/nmf.py
gensim/models/nmf_pgd.c
gensim-4.4.0.dist-info/licenses/COPYING
gensim-4.4.0.dist-info/METADATA
gensim-4.4.0.dist-info/WHEEL
gensim-4.4.0.dist-info/top_level.txt
gensim-4.4.0.dist-info/RECORD
