Metadata-Version: 2.1
Name: gensim
Version: 4.4.0
Summary: Python framework for fast Vector Space Modelling
Home-page: https://radimrehurek.com/gensim/
Download-URL: https://pypi.org/project/gensim/
Author: Radim Rehurek
Author-email: me@radimrehurek.com
License: LGPL-2.1-only
Project-URL: Source, https://github.com/RaRe-Technologies/gensim
Keywords: Singular Value Decomposition,SVD,Latent Semantic Indexing,LSA,LSI,Latent Dirichlet Allocation,LDA,Hierarchical Dirichlet Process,HDP,Random Projections,TFIDF,word2vec
Platform: any
Classifier: Development Status :: 5 - Production/Stable
Classifier: Environment :: Console
Classifier: Intended Audience :: Science/Research
Classifier: Operating System :: OS Independent
Classifier: Programming Language :: Python :: 3.9
Classifier: Programming Language :: Python :: 3.10
Classifier: Programming Language :: Python :: 3.11
Classifier: Programming Language :: Python :: 3.12
Classifier: Programming Language :: Python :: 3.13
Classifier: Programming Language :: Python :: 3 :: Only
Classifier: Topic :: Scientific/Engineering :: Artificial Intelligence
Classifier: Topic :: Scientific/Engineering :: Information Analysis
Classifier: Topic :: Text Processing :: Linguistic
Requires-Python: >=3.9
Provides-Extra: distributed
Provides-Extra: test-win
Provides-Extra: test
Provides-Extra: docs
License-File: COPYING
